arcl/__init__.py
arcl/__main__.py
arcl/auth.py
arcl/cli.py
arcl/config.py
arcl/token_cache.py
arcl-2.0.4.dist-info/METADATA
arcl-2.0.4.dist-info/WHEEL
arcl-2.0.4.dist-info/entry_points.txt
arcl-2.0.4.dist-info/RECORD
