Metadata-Version: 2.1
Name: arcl
Version: 2.0.4
Summary: The CLI for Archimedes
License: Apache-2.0
Author: Optimeering AS
Author-email: dev@optimeering.com
Requires-Python: >=3.9,<3.12
Classifier: License :: OSI Approved :: Apache Software License
Classifier: Programming Language :: Python :: 3
Classifier: Programming Language :: Python :: 3.9
Classifier: Programming Language :: Python :: 3.10
Classifier: Programming Language :: Python :: 3.11
Requires-Dist: click (>=8.1.3,<9.0.0)
Requires-Dist: msal (>=1.10.0,<2.0.0)
Requires-Dist: msal-extensions (>=1.0.0,<2.0.0)
Requires-Dist: requests
